pycancensus/__init__.py
pycancensus/cache.py
pycancensus/cli.py
pycancensus/core.py
pycancensus/datasets.py
pycancensus/geometry.py
pycancensus/hierarchy.py
pycancensus/intersect_geometry.py
pycancensus/progress.py
pycancensus/regions.py
pycancensus/resilience.py
pycancensus/settings.py
pycancensus/utils.py
pycancensus/vectors.py
pycancensus-0.1.0.dist-info/licenses/LICENSE
pycancensus-0.1.0.dist-info/METADATA
pycancensus-0.1.0.dist-info/WHEEL
pycancensus-0.1.0.dist-info/entry_points.txt
pycancensus-0.1.0.dist-info/top_level.txt
pycancensus-0.1.0.dist-info/RECORD
