Metadata-Version: 2.4
Name: pycancensus
Version: 0.1.0
Summary: Access, retrieve, and work with Canadian Census data and geography
Author-email: Dmitry Shkolnik <shkolnikd@gmail.com>
License: MIT
Project-URL: Homepage, https://github.com/dshkol/pycancensus
Project-URL: Repository, https://github.com/dshkol/pycancensus
Project-URL: Documentation, https://pycancensus.readthedocs.io
Project-URL: Bug Tracker, https://github.com/dshkol/pycancensus/issues
Classifier: Development Status :: 3 - Alpha
Classifier: Intended Audience :: Science/Research
Classifier: License :: OSI Approved :: MIT License
Classifier: Operating System :: OS Independent
Classifier: Programming Language :: Python :: 3
Classifier: Programming Language :: Python :: 3.7
Classifier: Programming Language :: Python :: 3.8
Classifier: Programming Language :: Python :: 3.9
Classifier: Programming Language :: Python :: 3.10
Classifier: Programming Language :: Python :: 3.11
Classifier: Topic :: Scientific/Engineering
Classifier: Topic :: Scientific/Engineering :: GIS
Requires-Python: >=3.7
License-File: LICENSE
Requires-Dist: requests>=2.25.0
Requires-Dist: pandas>=1.0.0
Requires-Dist: geopandas>=0.8.0
Provides-Extra: dev
Requires-Dist: pytest>=6.0; extra == "dev"
Requires-Dist: pytest-cov; extra == "dev"
Requires-Dist: black; extra == "dev"
Requires-Dist: flake8; extra == "dev"
Provides-Extra: docs
Requires-Dist: sphinx>=4.0; extra == "docs"
Requires-Dist: sphinx-rtd-theme; extra == "docs"
Requires-Dist: myst-nb>=0.17; extra == "docs"
Requires-Dist: sphinx-gallery>=0.11; extra == "docs"
Requires-Dist: sphinx-autosummary-accessors; extra == "docs"
Requires-Dist: sphinx-copybutton; extra == "docs"
Requires-Dist: matplotlib>=3.4.0; extra == "docs"
Requires-Dist: folium>=0.12.0; extra == "docs"
Provides-Extra: cross-validation
Requires-Dist: rpy2>=3.4.0; extra == "cross-validation"
Requires-Dist: tqdm>=4.62.0; extra == "cross-validation"
Requires-Dist: deepdiff>=5.6.0; extra == "cross-validation"
Requires-Dist: tabulate>=0.8.9; extra == "cross-validation"
Requires-Dist: matplotlib>=3.4.0; extra == "cross-validation"
Requires-Dist: seaborn>=0.11.0; extra == "cross-validation"
Dynamic: license-file
